[
  {
    "name": "SVG to Image",
    "path": "svg2img",
    "view": "",
    "desc": "Convert SVG to image."
  },
  {
    "name": "Image Comparison Tool",
    "path": "",
    "view": "https://ict.ehhh.eu.org/",
    "desc": "Compare two images or videos in your browser side by side."
  },
  {
    "name": "pangu.js Demo",
    "path": "pangu",
    "view": "",
    "desc": "Insert whitespace between CJK and half-width characters."
  },
  {
    "name": "MS Pinyin UDP Manager",
    "path": "mspyudpmgr",
    "view": "",
    "desc": "Parse and dump MS Pinyin IME user defined phrases."
  },
  {
    "name": "Minifier",
    "path": "",
    "view": "https://hm.ehhh.eu.org/",
    "desc": "Online HTML/JS/CSS Minifier."
  },
  {
    "name": "Hashtag Parser",
    "path": "danbooru/hashtagparser",
    "view": "",
    "desc": "Convert plain text hashtag to Danbooru DText."
  },
  {
    "name": "JSON Editor",
    "path": "jsoneditor",
    "view": "",
    "desc": "JSON Editor."
  },
  {
    "name": "Font Metadata Viewer",
    "path": "fontmetaviewer",
    "view": "",
    "desc": "Supported formats: TTF, OTF, WOFF, WOFF2."
  }
]
